Metadata-Version: 2.1
Name: comchoice
Version: 0.1.3
Summary: ComChoice (Computational Choice) is a large collection of many well-known voting rules and aggregation methods in Python.
Home-page: https://github.com/CenterForCollectiveLearning/comchoice
Author: cnavarreteliz
Author-email: cnavarreteliz@gmail.com
Classifier: Programming Language :: Python :: 3
Classifier: Programming Language :: Python :: 3.7
Classifier: Programming Language :: Python :: 3.8
Classifier: Programming Language :: Python :: 3.9
Classifier: Programming Language :: Python :: 3.10
License-File: LICENSE.md
Requires-Dist: fastapi
Requires-Dist: networkx
Requires-Dist: numpy
Requires-Dist: pandas
Requires-Dist: requests
Requires-Dist: scipy
Requires-Dist: tqdm
